{
    "backend": "api-server-nodejs",
    "db_name": "",
    "db_pass": "",
    "db_type": "sqlite",
    "db_user": "",
    "dbms": "1",
    "description": "generated product",
    "design": "berry-dashboard",
    "docker": "0",
    "err_code": 0,
    "frontend": "react",
    "heroku": "0",
    "pattern": "fullstack",
    "pro": "0",
    "task_id": "d85680c6-57bd-4de2-a3db-48a1d082f638",
    "task_info": "Upload Sources [0%] - 144 files",
    "task_output": "d85680c6-57bd-4de2-a3db-48a1d082f638.zip",
    "task_result": "SUCCESS",
    "task_state": "RUNNING",
    "task_ts_end": "2023-03-05-12-38-10",
    "task_ts_start": "2023-03-05-12-38-09"
}